{
  "variantName": "cards-dark",
  "baseBlock": "cards",
  "version": "1.0.0",
  "created": "2026-04-06T08:13:00.000Z",
  "sourceContext": {
    "originUrl": "https://www.royalenfield.com/in/en/home/",
    "originPage": "Royal Enfield India homepage",
    "blockPosition": "middle"
  },
  "visualCharacteristics": {
    "colorScheme": "dark",
    "density": "compact",
    "purpose": "product-grid",
    "imagePattern": "large"
  },
  "contentPattern": {
    "structure": "image + heading + description",
    "buttonCount": 0,
    "imageCount": 1
  },
  "reuseGuidance": {
    "suitableFor": [
      "dark-themed product/category grids",
      "image-heavy card layouts",
      "motorcycle/vehicle listings",
      "event listings with images"
    ],
    "notSuitableFor": [
      "light-themed card grids",
      "text-only card layouts",
      "icon-based feature lists"
    ]
  },
  "usage": {
    "pagesUsing": ["/in/en/home/index"],
    "reuseCount": 1,
    "lastUsed": "2026-04-06T08:13:00.000Z"
  }
}
